genx/__init__.py
genx/__main__.py
genx/api.py
genx/bumps_optimizer.py
genx/data.py
genx/diffev.py
genx/exceptions.py
genx/fom_funcs.py
genx/levenberg_marquardt.py
genx/model.py
genx/model_actions.py
genx/model_control.py
genx/parameters.py
genx/run.py
genx/server.py
genx/solver_basis.py
genx/version.py
genx/core/Simplex.py
genx/core/__init__.py
genx/core/colors.py
genx/core/config.py
genx/core/console.py
genx/core/custom_logging.py
genx/core/decorators.py
genx/core/h5_support.py
genx/examples/D17_SiO.out
genx/examples/D17_TOF_SiO.hgx
genx/examples/Neutron_SiO_ref.dat
genx/examples/Peakfit_Gauss.hgx
genx/examples/Peakfit_Gauss_coupled_pars.hgx
genx/examples/Peakfit_Voigt.hgx
genx/examples/SXRD.hgx
genx/examples/SXRD2.hgx
genx/examples/SuperAdam_SiO.hgx
genx/examples/SuperAdam_SiO_advanced_fp_res.hgx
genx/examples/SuperAdam_SiO_full_res_calc.hgx
genx/examples/SuperAdam_SiO_systematic_errors.hgx
genx/examples/X-ray_Reflectivity.hgx
genx/examples/X-ray_Reflectivity_kalpha.hgx
genx/examples/bumps_integration.ipynb
genx/examples/load_fit_save.ipynb
genx/examples/publication_graphics.ipynb
genx/examples/reflectivity_interface.ipynb
genx/examples/widget_test.ipynb
genx/examples/xray-tutorial.dat
genx/models/__init__.py
genx/models/interdiff.py
genx/models/mag_refl.py
genx/models/soft_nx.py
genx/models/spec_adaptive.py
genx/models/spec_inhom.py
genx/models/spec_nx.py
genx/models/sxrd.py
genx/models/sxrd2.py
genx/models/sxrd_mult.py
genx/models/symmetries.py
genx/models/utils.py
genx/models/databases/AtomicWeights.dat
genx/models/databases/DeBe_NeutronNews.dat
genx/models/databases/download_nist.py
genx/models/databases/f0_CromerMann.dat
genx/models/databases/f1f2_Chantler.dat
genx/models/databases/f1f2_cxro/ac.nff
genx/models/databases/f1f2_cxro/ag.nff
genx/models/databases/f1f2_cxro/al.nff
genx/models/databases/f1f2_cxro/ar.nff
genx/models/databases/f1f2_cxro/as.nff
genx/models/databases/f1f2_cxro/at.nff
genx/models/databases/f1f2_cxro/au.nff
genx3server-3.7.14.dist-info/licenses/LICENSE.txt
genx3server-3.7.14.dist-info/METADATA
genx3server-3.7.14.dist-info/WHEEL
genx3server-3.7.14.dist-info/entry_points.txt
genx3server-3.7.14.dist-info/top_level.txt
genx3server-3.7.14.dist-info/RECORD
